aiobasex/__init__.py
aiobasex/connection.py
aiobasex/errors.py
aiobasex/query.py
aiobasex/session.py
aiobasex/utils.py
aiobasex-0.0.1.dist-info/DESCRIPTION.rst
aiobasex-0.0.1.dist-info/METADATA
aiobasex-0.0.1.dist-info/RECORD
aiobasex-0.0.1.dist-info/WHEEL
aiobasex-0.0.1.dist-info/metadata.json
aiobasex-0.0.1.dist-info/top_level.txt
